Verilog/Magnitud Comparer/MC_2bits/MC_2bit.v
module MC_2bit (

    input wire a0, a1, b0, b1,
    output wire c, // A<B
    output wire d, // A>B
    output wire e  // A=B

);

wire f, g;

assign f = ~(a1 ^ b1);
assign g = ~(a0 ^ b0);

assign c = (~a1 & b1) | (~a0 & b0 & f);
assign d = (a0 & ~b0 & f) | (a1 & ~b1);
assign e = (f & g);
   
endmodule

Verilog/Magnitud Comparer/MC_2bits/MC_2bit_tb.v
`timescale  1ns/1ps

module MC_2bit_tb;

reg a0; 
reg a1;
reg b0;
reg b1;

wire c; 
wire d;
wire e;
wire f;
wire g;

MC_2bit uut(
    .a0(a0),
    .a1(a1),
    .b0(b0),
    .b1(b1),

    .c(c),
    .d(d),
    .e(e),
    .f(f),
    .g(g)
);

initial begin 
    $dumpfile("sim.vcd");
    $dumpvars(0, MC_2bit_tb );

    $monitor("t=%0d | a1=%b a0=%b b1=%b  b0=%b | A < B=%0b | A = E =%b | A > B=%b ", $time, a1, a0, b1, b0, c, e, d);


       a1 = 0; a0 = 0; b1 = 0; b0 = 0;  #10;
       a1 = 0; a0 = 0; b1 = 0; b0 = 1;  #10;
       a1 = 0; a0 = 0; b1 = 1; b0 = 0;  #10;
       a1 = 0; a0 = 0; b1 = 1; b0 = 1;  #10;
       a1 = 0; a0 = 1; b1 = 0; b0 = 0;  #10;
       a1 = 0; a0 = 1; b1 = 0; b0 = 1;  #10;
       a1 = 0; a0 = 1; b1 = 1; b0 = 0;  #10;
       a1 = 0; a0 = 1; b1 = 1; b0 = 1;  #10;
       a1 = 1; a0 = 0; b1 = 0; b0 = 0;  #10;
       a1 = 1; a0 = 0; b1 = 0; b0 = 1;  #10;
       a1 = 1; a0 = 0; b1 = 1; b0 = 0;  #10;
       a1 = 1; a0 = 0; b1 = 1; b0 = 1;  #10;
       a1 = 1; a0 = 1; b1 = 0; b0 = 0;  #10;
       a1 = 1; a0 = 1; b1 = 0; b0 = 1;  #10;
       a1 = 1; a0 = 1; b1 = 1; b0 = 0;  #10;
       a1 = 1; a0 = 1; b1 = 1; b0 = 1;  #10;
       
     

      $display("===Fin de la simulacion===");
      $finish;

end
endmodule

Verilog/Magnitud Comparer/MC_2bits/sim.vcd
$date
	Sun Apr 05 15:05:34 2026
$end
$version
	Icarus Verilog
$end
$timescale
	1ps
$end
$scope module MC_2bit_tb $end
$var wire 1 ! g $end
$var wire 1 " f $end
$var wire 1 # e $end
$var wire 1 $ d $end
$var wire 1 % c $end
$var reg 1 & a0 $end
$var reg 1 ' a1 $end
$var reg 1 ( b0 $end
$var reg 1 ) b1 $end
$scope module uut $end
$var wire 1 & a0 $end
$var wire 1 ' a1 $end
$var wire 1 ( b0 $end
$var wire 1 ) b1 $end
$var wire 1 % c $end
$var wire 1 $ d $end
$var wire 1 # e $end
$var wire 1 " f $end
$var wire 1 ! g $end
$upscope $end
$upscope $end
$enddefinitions $end
$comment Show the parameter values. $end
$dumpall
$end
#0
$dumpvars
0)
0(
0'
0&
0%
0$
1#
1"
1!
$end
#10000
1%
0#
0!
1(
#20000
1!
0"
0(
1)
#30000
0!
1(
#40000
1$
0%
1"
0(
0)
1&
#50000
0$
1#
1!
1(
#60000
0#
0!
1%
0"
0(
1)
#70000
1!
1(
#80000
1$
0%
0(
0)
0&
1'
#90000
0!
1(
#100000
1#
0$
1!
1"
0(
1)
#110000
1%
0#
0!
1(
#120000
0%
1$
0"
0(
0)
1&
#130000
1!
1(
#140000
1$
0!
1"
0(
1)
#150000
0$
1#
1!
1(
