Verilog/Chip 7458/7458.v
module chip7458 (
    input wire p1a, p2a, p2b, p2c, p2d, p1c, p1b, p1f, p1e, p1d,
    output wire p2y, p1y
);
   
assign p2y = (p2a & p2b) | (p2c & p2d );

assign p1y = (p1c & p1b & p1a) | (p1f & p1e & p1d  );

endmodule

Verilog/Chip 7458/7458_tb.v
`timescale 1ns/1ps

module chip7458_tb;

reg p1a, p2a, p2b, p2c, p2d, p1c, p1b, p1f, p1e, p1d;

wire p2y, p1y;

chip7458 utt(
    .p1a(p1a),
    .p2a(p2a),
    .p2b(p2b),
    .p2c(p2c),
    .p2d(p2d),
    .p1c(p1c),
    .p1b(p1b),
    .p1f(p1f),
    .p1e(p1e),
    .p1d(p1d)
);

initial begin
    $dumpfile("chip7458.vcd");
    $dumpvars(0, chip7458_tb);
    $monitor("t=%0d | p1a=%b  p1b=%b p1c=%b p1d=%b p1e=%b p1f=%b p2a=%b p2b=%b p2c=%b p2d=%b | p2y=%b p1y=%b", $time, p1a, p1b, p1c, p1d, p1e, p1f, p2a, p2b, p2c, p2d,  p2y, p1y );

    p1a=0; p1b=0; p1c=0; p1d=0; p1e=0; p1f=0; p2a=0; p2b=0; p2c=0; p2d=0; #10;

     // --- Pruebas p2y = (p2a & p2b) | (p2c & p2d) ---

    p2a=1; p2b=1; p2c=0; p2d=0; #10;

   
    p2a=0; p2b=0; p2c=1; p2d=1; #10;

   
    p2a=1; p2b=1; p2c=1; p2d=1; #10;

  
    p2a=1; p2b=0; p2c=1; p2d=0; #10;

    
    p2a=0; p2b=0; p2c=0; p2d=0; #10;

    // --- Pruebas p1y = (p1a & p1b & p1c) | (p1d & p1e & p1f) ---

  
    p1a=1; p1b=1; p1c=1; p1d=0; p1e=0; p1f=0; #10;

    
    p1a=0; p1b=0; p1c=0; p1d=1; p1e=1; p1f=1; #10;

  
    p1a=1; p1b=1; p1c=1; p1d=1; p1e=1; p1f=1; #10;

  
    p1a=1; p1b=1; p1c=0; p1d=0; p1e=0; p1f=0; #10;


    p1a=0; p1b=0; p1c=0; p1d=1; p1e=1; p1f=0; #10;


    p1a=1; p1b=1; p1c=1; p1d=1; p1e=1; p1f=1;
    p2a=1; p2b=1; p2c=1; p2d=1; #10;
    
    $finish;
end

endmodule

Verilog/Chip 7458/chip7458.vcd
$date
	Sun Apr 19 20:39:16 2026
$end
$version
	Icarus Verilog
$end
$timescale
	1ps
$end
$scope module chip7458_tb $end
$var wire 1 ! p1y $end
$var wire 1 " p2y $end
$var reg 1 # p1a $end
$var reg 1 $ p1b $end
$var reg 1 % p1c $end
$var reg 1 & p1d $end
$var reg 1 ' p1e $end
$var reg 1 ( p1f $end
$var reg 1 ) p2a $end
$var reg 1 * p2b $end
$var reg 1 + p2c $end
$var reg 1 , p2d $end
$scope module utt $end
$var wire 1 # p1a $end
$var wire 1 $ p1b $end
$var wire 1 % p1c $end
$var wire 1 & p1d $end
$var wire 1 ' p1e $end
$var wire 1 ( p1f $end
$var wire 1 - p1y $end
$var wire 1 ) p2a $end
$var wire 1 * p2b $end
$var wire 1 + p2c $end
$var wire 1 , p2d $end
$var wire 1 . p2y $end
$upscope $end
$upscope $end
$enddefinitions $end
$comment Show the parameter values. $end
$dumpall
$end
#0
$dumpvars
0.
0-
0,
0+
0*
0)
0(
0'
0&
0%
0$
0#
z"
z!
$end
#10000
1.
1*
1)
#20000
1,
1+
0*
0)
#30000
1*
1)
#40000
0.
0,
0*
#50000
0+
0)
#60000
1-
1%
1$
1#
#70000
1-
1(
1'
1&
0%
0$
0#
#80000
1%
1$
1#
#90000
0-
0(
0'
0&
0%
#100000
1'
1&
0$
0#
#110000
1-
1.
1,
1+
1*
1)
1(
1%
1$
1#
