Verilog/Adder/Adder.v
module Adder (
    input wire a, b, cin,
    output wire s, cout
);

    assign s = (a^b^cin);
    assign cout = ((b&a) | ((b|a) & cin));
    
endmodule

Verilog/Adder/Adder_tb.v
`timescale 1ns/1ps

module Adder_tb;

reg a, b, cin;
wire s, cout;

Adder utt(
    .a    (a),
    .b    (b),
    .cin  (cin),
    .s    (s),
    .cout (cout)
);


initial begin
    $dumpfile("adder.vcd");
    $dumpvars(0, Adder_tb);
    $monitor("t=%0t | a=%b b=%b cin=%b | s=%b cout=%b", $time, a, b, cin, s, cout);

    a=0; b=0; cin=0; #10;
    a=1; b=0; cin=0; #10;
    a=0; b=1; cin=0; #10;
    a=1; b=1; cin=0; #10;
    a=1; b=0; cin=1; #10;
    a=0; b=1; cin=1; #10;
    a=1; b=1; cin=1; #10;
    a=0; b=0; cin=1; #10;
    
    $display("===Fin de la simulacion==");
    $finish;

end


endmodule

Verilog/Adder/adder.vcd
$date
	Fri Apr 03 18:48:12 2026
$end
$version
	Icarus Verilog
$end
$timescale
	1ps
$end
$scope module Adder_tb $end
$var wire 1 ! s $end
$var wire 1 " cout $end
$var reg 1 # a $end
$var reg 1 $ b $end
$var reg 1 % cin $end
$scope module utt $end
$var wire 1 # a $end
$var wire 1 $ b $end
$var wire 1 % cin $end
$var wire 1 " cout $end
$var wire 1 ! s $end
$upscope $end
$upscope $end
$enddefinitions $end
$comment Show the parameter values. $end
$dumpall
$end
#0
$dumpvars
0%
0$
0#
0"
0!
$end
#10000
1!
1#
#20000
1$
0#
#30000
0!
1"
1#
#40000
1%
0$
#50000
1$
0#
#60000
1!
1#
#70000
0"
0$
0#
