Verilog/Calculator/Calculadora.v
`timescale 1ns/1ps

module calculadora(
    input clk,
    input clr,
    input guardar,
    input [3:0] op,
    input [3:0] a,
    input [3:0] b,
    output reg [7:0] c,
    output reg [7:0] resultado,
    output reg [11:0] bcd

);

integer i;


wire guardar_i = (op== 4'b0101);
wire clr_i =     (op== 4'b0110);

always @(*)
    begin
        case (op)

            4'b0000 : c= a + b; 
            4'b0001 : c= a - b;
            4'b0010 : c= a / b;
            4'b0011 : c= a * b;
            4'b0100 : c= a ** b;
            4'b0111 : c= resultado;
            default : c= 8'b0;

        endcase


    end



always @(*)
    
    begin
        bcd=0;

            for (i =0; i < 8; i= i+1 ) begin
                

                //verificacion 
                if(bcd[3:0] > 4)
                    bcd[3:0] = bcd[3:0]+3;
                if(bcd[7:4] > 4)
                    bcd[7:4] = bcd[7:4]+3;
                if(bcd[11:8] > 4)
                    bcd[11:8] = bcd[11:8]+3;
              
              //primer shift 
                bcd= {bcd[10:0], c[7-i]};

            end

    end

always @(posedge clk) begin

    if(clr || clr_i)
        resultado <= 8'b0;
    else if(guardar || guardar_i)
        resultado <= c;
        
end

endmodule

Verilog/Calculator/Calculadora_tb.v
`timescale 1ns/1ps

module Calculadora_tb;


reg [3:0] op, a, b;
reg clk, clr, guardar;

wire [7:0] resultado;
wire [7:0] c;
wire [11:0] bcd;

calculadora uut(
    .clk(clk),
    .clr(clr),
    .guardar(guardar),
    .a(a),
    .b(b),
    .op(op),
    .c(c),
    .resultado(resultado),
    .bcd(bcd)
);

initial clk=0;
always #10 clk=~clk;


initial begin
    $dumpfile("Calculadora.vcd");
    $dumpvars(0, Calculadora_tb);

    $monitor("t=%0d | a=%d b=%d op=%b | c=%d resultado=%d  bcd =%b", 
    $time, a, b, op, c, resultado, bcd);


        clr= 0; guardar= 0;
        a=0; b=0; op=4'b0000;

        @(posedge clk ); #10;
        op= 4'b0000;
        a= 4'b0101; b= 4'b0011; 
        @(posedge clk); #10;
        $display("Suma 5 +3 -> c=%0d  bcd=%0b", c, bcd);

    //guardar
        @(posedge clk ); #10;
        guardar=1;
        @(posedge clk); #10;
        guardar=0;
        $display("Guardar-> resultado=%0d", resultado); 

    // multiplicacion: 3 * 4 = 12
        @(posedge clk); #1;
        a = 4'd3; b = 4'd4; op = 4'b0011;
        @(posedge clk); #1;
        $display("MULT 3*4 -> c=%0d bcd=%b", c, bcd);

    // mostrar resultado guardado via op=0111
        @(posedge clk); #1;
        op = 4'b0111;
        @(posedge clk); #1;
        $display("MOSTRAR GUARDADO -> c=%0d bcd=%b", c, bcd);
    
     // limpiar via op=0110
        @(posedge clk); #1;
        op = 4'b0110;
        @(posedge clk); #1;
        $display("CLR -> resultado=%0d", resultado);

    repeat(3) @(posedge clk);
    $display("===Fin de la simulacion===");
    $finish;

end
     
endmodule

Verilog/Calculator/Calculadora.vcd
$date
	Thu Apr 09 19:36:04 2026
$end
$version
	Icarus Verilog
$end
$timescale
	1ps
$end
$scope module Calculadora_tb $end
$var wire 8 ! resultado [7:0] $end
$var wire 8 " c [7:0] $end
$var wire 12 # bcd [11:0] $end
$var reg 4 $ a [3:0] $end
$var reg 4 % b [3:0] $end
$var reg 1 & clk $end
$var reg 1 ' clr $end
$var reg 1 ( guardar $end
$var reg 4 ) op [3:0] $end
$scope module uut $end
$var wire 4 * a [3:0] $end
$var wire 4 + b [3:0] $end
$var wire 1 & clk $end
$var wire 1 ' clr $end
$var wire 1 ( guardar $end
$var wire 4 , op [3:0] $end
$var wire 1 - guardar_i $end
$var wire 1 . clr_i $end
$var reg 12 / bcd [11:0] $end
$var reg 8 0 c [7:0] $end
$var reg 8 1 resultado [7:0] $end
$var integer 32 2 i [31:0] $end
$upscope $end
$upscope $end
$enddefinitions $end
$comment Show the parameter values. $end
$dumpall
$end
#0
$dumpvars
b1000 2
bx 1
b0 0
b0 /
0.
0-
b0 ,
b0 +
b0 *
b0 )
0(
0'
0&
b0 %
b0 $
b0 #
b0 "
bx !
$end
#10000
1&
#20000
b1000 #
b1000 /
b1000 2
b1000 "
b1000 0
b11 %
b11 +
b101 $
b101 *
0&
#30000
1&
#40000
0&
#50000
1&
#60000
1(
0&
#70000
b1000 !
b1000 1
1&
#80000
0(
0&
#90000
1&
#91000
b1000 2
b10010 #
b10010 /
b1100 "
b1100 0
b11 )
b11 ,
b100 %
b100 +
b11 $
b11 *
#100000
0&
#110000
1&
#120000
0&
#130000
1&
#131000
b1000 2
b1000 #
b1000 /
b1000 "
b1000 0
b111 )
b111 ,
#140000
0&
#150000
1&
#160000
0&
#170000
1&
#171000
b1000 2
b0 #
b0 /
b0 "
b0 0
1.
b110 )
b110 ,
#180000
0&
#190000
b0 !
b0 1
1&
