Verilog/Magnitud Comparer/MC_4bits/MC_4bit.v
module MC_4bit (

    input wire a0, a1, a2, a3, b0, b1, b2, b3,
    output wire c, // A<B
    output wire d, // A>B
    output wire e  // A=B

);

wire f, g, h, j;

assign j = ~(a3 ^ b3);
assign h = ~(a2 ^ b2);
assign f = ~(a1 ^ b1);
assign g = ~(a0 ^ b0);


assign c = (f & h & j & ~b0 & a0) | (j & h & ~b1 & a1) | (j &  ~b2 & a2) | (~b3 & a3);
assign d = (b3 & ~a3) | (b2 & ~a2 & j) | (b1 & ~a1 & h & j) | (b0 & ~a0 & j & h & f);
assign e = (f & g & h & j);
   
endmodule

Verilog/Magnitud Comparer/MC_4bits/MC_4bit_tb.v
`timescale  1ns/1ps

module MC_2bit_tb;

reg [3:0] A; 
reg [3:0] B;

wire c, d, e; 

MC_4bit uut(
    .a0(A[0]), .a1(A[1]), .a2(A[2]), .a3(A[3]),
    .b0(B[0]), .b1(B[1]), .b2(B[2]), .b3(B[3]),
    .c(c), .d(d), .e(e)
);


integer i;

initial begin 
    $dumpfile("sim.vcd");
    $dumpvars(0, MC_2bit_tb );

    $monitor("t=%0d | A=%b B=%b | A < B=%0b | A==E=%b | A > B=%b ", 
                $time, A, B, c, e, d);


    for( i=0; i<256; i=i+1)
    begin
        A=i[7:4];
        B=i[3:0];
        #10;
    end

      $display("===Fin de la simulacion===");
      $finish;

end
endmodule

Verilog/Magnitud Comparer/MC_4bits/sim.vcd
$date
	Sun Apr 05 15:41:17 2026
$end
$version
	Icarus Verilog
$end
$timescale
	1ps
$end
$scope module MC_2bit_tb $end
$var wire 1 ! e $end
$var wire 1 " d $end
$var wire 1 # c $end
$var reg 4 $ A [3:0] $end
$var reg 4 % B [3:0] $end
$var integer 32 & i [31:0] $end
$scope module uut $end
$var wire 1 ' a0 $end
$var wire 1 ( a1 $end
$var wire 1 ) a2 $end
$var wire 1 * a3 $end
$var wire 1 + b0 $end
$var wire 1 , b1 $end
$var wire 1 - b2 $end
$var wire 1 . b3 $end
$var wire 1 # c $end
$var wire 1 " d $end
$var wire 1 ! e $end
$var wire 1 / f $end
$var wire 1 0 g $end
$var wire 1 1 h $end
$var wire 1 2 j $end
$upscope $end
$upscope $end
$enddefinitions $end
$comment Show the parameter values. $end
$dumpall
$end
#0
$dumpvars
12
11
10
1/
0.
0-
0,
0+
0*
0)
0(
0'
b0 &
b0 %
b0 $
0#
0"
1!
$end
#10000
0!
1"
00
1+
b1 %
b1 &
#20000
10
0/
0+
1,
b10 %
b10 &
#30000
00
1+
b11 %
b11 &
#40000
10
1/
01
0+
0,
1-
b100 %
b100 &
#50000
00
1+
b101 %
b101 &
#60000
10
0/
0+
1,
b110 %
b110 &
#70000
00
1+
b111 %
b111 &
#80000
10
1/
11
02
0+
0,
0-
1.
b1000 %
b1000 &
#90000
00
1+
b1001 %
b1001 &
#100000
10
0/
0+
1,
b1010 %
b1010 &
#110000
00
1+
b1011 %
b1011 &
#120000
10
1/
01
0+
0,
1-
b1100 %
b1100 &
#130000
00
1+
b1101 %
b1101 &
#140000
10
0/
0+
1,
b1110 %
b1110 &
#150000
00
1+
b1111 %
b1111 &
#160000
1#
0"
1/
11
12
0+
0,
0-
0.
1'
b0 %
b1 $
b10000 &
#170000
0#
1!
10
1+
b1 %
b10001 &
#180000
0#
0!
1"
00
0/
0+
1,
b10 %
b10010 &
#190000
10
1+
b11 %
b10011 &
#200000
00
1/
01
0+
0,
1-
b100 %
b10100 &
#210000
10
1+
b101 %
b10101 &
#220000
00
0/
0+
1,
b110 %
b10110 &
#230000
10
1+
b111 %
b10111 &
#240000
00
1/
11
02
0+
0,
0-
1.
b1000 %
b11000 &
#250000
10
1+
b1001 %
b11001 &
#260000
00
0/
0+
1,
b1010 %
b11010 &
#270000
10
1+
b1011 %
b11011 &
#280000
00
1/
01
0+
0,
1-
b1100 %
b11100 &
#290000
10
1+
b1101 %
b11101 &
#300000
00
0/
0+
1,
b1110 %
b11110 &
#310000
10
1+
b1111 %
b11111 &
#320000
1#
0"
11
12
0+
0,
0-
0.
0'
1(
b0 %
b10 $
b100000 &
#330000
00
1+
b1 %
b100001 &
#340000
0#
1!
0"
10
1/
0+
1,
b10 %
b100010 &
#350000
0!
1"
00
1+
b11 %
b100011 &
#360000
0#
10
0/
01
0+
0,
1-
b100 %
b100100 &
#370000
00
1+
b101 %
b100101 &
#380000
10
1/
0+
1,
b110 %
b100110 &
#390000
00
1+
b111 %
b100111 &
#400000
10
0/
11
02
0+
0,
0-
1.
b1000 %
b101000 &
#410000
00
1+
b1001 %
b101001 &
#420000
10
1/
0+
1,
b1010 %
b101010 &
#430000
00
1+
b1011 %
b101011 &
#440000
10
0/
01
0+
0,
1-
b1100 %
b101100 &
#450000
00
1+
b1101 %
b101101 &
#460000
10
1/
0+
1,
b1110 %
b101110 &
#470000
00
1+
b1111 %
b101111 &
#480000
1#
0"
0/
11
12
0+
0,
0-
0.
1'
b0 %
b11 $
b110000 &
#490000
10
1+
b1 %
b110001 &
#500000
1#
00
1/
0+
1,
b10 %
b110010 &
#510000
0#
1!
10
1+
b11 %
b110011 &
#520000
0#
1"
0!
00
0/
01
0+
0,
1-
b100 %
b110100 &
#530000
10
1+
b101 %
b110101 &
#540000
00
1/
0+
1,
b110 %
b110110 &
#550000
10
1+
b111 %
b110111 &
#560000
00
0/
11
02
0+
0,
0-
1.
b1000 %
b111000 &
#570000
10
1+
b1001 %
b111001 &
#580000
00
1/
0+
1,
b1010 %
b111010 &
#590000
10
1+
b1011 %
b111011 &
#600000
00
0/
01
0+
0,
1-
b1100 %
b111100 &
#610000
10
1+
b1101 %
b111101 &
#620000
00
1/
0+
1,
b1110 %
b111110 &
#630000
10
1+
b1111 %
b111111 &
#640000
1#
0"
12
0+
0,
0-
0.
0'
0(
1)
b0 %
b100 $
b1000000 &
#650000
00
1+
b1 %
b1000001 &
#660000
10
0/
0+
1,
b10 %
b1000010 &
#670000
00
1+
b11 %
b1000011 &
#680000
1!
0#
10
1/
11
0+
0,
1-
b100 %
b1000100 &
#690000
0!
1"
00
1+
b101 %
b1000101 &
#700000
10
0/
0+
1,
b110 %
b1000110 &
#710000
00
1+
b111 %
b1000111 &
#720000
10
1/
01
02
0+
0,
0-
1.
b1000 %
b1001000 &
#730000
00
1+
b1001 %
b1001001 &
#740000
10
0/
0+
1,
b1010 %
b1001010 &
#750000
00
1+
b1011 %
b1001011 &
#760000
10
1/
11
0+
0,
1-
b1100 %
b1001100 &
#770000
00
1+
b1101 %
b1001101 &
#780000
10
0/
0+
1,
b1110 %
b1001110 &
#790000
00
1+
b1111 %
b1001111 &
#800000
1#
0"
1/
01
12
0+
0,
0-
0.
1'
b0 %
b101 $
b1010000 &
#810000
10
1+
b1 %
b1010001 &
#820000
00
0/
0+
1,
b10 %
b1010010 &
#830000
10
1+
b11 %
b1010011 &
#840000
1#
00
1/
11
0+
0,
1-
b100 %
b1010100 &
#850000
0#
1!
10
1+
b101 %
b1010101 &
#860000
0#
0!
1"
00
0/
0+
1,
b110 %
b1010110 &
#870000
10
1+
b111 %
b1010111 &
#880000
00
1/
01
02
0+
0,
0-
1.
b1000 %
b1011000 &
#890000
10
1+
b1001 %
b1011001 &
#900000
00
0/
0+
1,
b1010 %
b1011010 &
#910000
10
1+
b1011 %
b1011011 &
#920000
00
1/
11
0+
0,
1-
b1100 %
b1011100 &
#930000
10
1+
b1101 %
b1011101 &
#940000
00
0/
0+
1,
b1110 %
b1011110 &
#950000
10
1+
b1111 %
b1011111 &
#960000
1#
0"
01
12
0+
0,
0-
0.
0'
1(
b0 %
b110 $
b1100000 &
#970000
00
1+
b1 %
b1100001 &
#980000
10
1/
0+
1,
b10 %
b1100010 &
#990000
00
1+
b11 %
b1100011 &
#1000000
1#
10
0/
11
0+
0,
1-
b100 %
b1100100 &
#1010000
00
1+
b101 %
b1100101 &
#1020000
0#
1!
0"
10
1/
0+
1,
b110 %
b1100110 &
#1030000
0!
1"
00
1+
b111 %
b1100111 &
#1040000
0#
10
0/
01
02
0+
0,
0-
1.
b1000 %
b1101000 &
#1050000
00
1+
b1001 %
b1101001 &
#1060000
10
1/
0+
1,
b1010 %
b1101010 &
#1070000
00
1+
b1011 %
b1101011 &
#1080000
10
0/
11
0+
0,
1-
b1100 %
b1101100 &
#1090000
00
1+
b1101 %
b1101101 &
#1100000
10
1/
0+
1,
b1110 %
b1101110 &
#1110000
00
1+
b1111 %
b1101111 &
#1120000
1#
0"
0/
01
12
0+
0,
0-
0.
1'
b0 %
b111 $
b1110000 &
#1130000
10
1+
b1 %
b1110001 &
#1140000
00
1/
0+
1,
b10 %
b1110010 &
#1150000
10
1+
b11 %
b1110011 &
#1160000
1#
0!
00
0/
11
0+
0,
1-
b100 %
b1110100 &
#1170000
10
1+
b101 %
b1110101 &
#1180000
1#
00
1/
0+
1,
b110 %
b1110110 &
#1190000
0#
1!
10
1+
b111 %
b1110111 &
#1200000
0#
1"
0!
00
0/
01
02
0+
0,
0-
1.
b1000 %
b1111000 &
#1210000
10
1+
b1001 %
b1111001 &
#1220000
00
1/
0+
1,
b1010 %
b1111010 &
#1230000
10
1+
b1011 %
b1111011 &
#1240000
00
0/
11
0+
0,
1-
b1100 %
b1111100 &
#1250000
10
1+
b1101 %
b1111101 &
#1260000
00
1/
0+
1,
b1110 %
b1111110 &
#1270000
10
1+
b1111 %
b1111111 &
#1280000
0"
1#
0+
0,
0-
0.
0'
0(
0)
1*
b0 %
b1000 $
b10000000 &
#1290000
00
1+
b1 %
b10000001 &
#1300000
10
0/
0+
1,
b10 %
b10000010 &
#1310000
00
1+
b11 %
b10000011 &
#1320000
10
1/
01
0+
0,
1-
b100 %
b10000100 &
#1330000
00
1+
b101 %
b10000101 &
#1340000
10
0/
0+
1,
b110 %
b10000110 &
#1350000
00
1+
b111 %
b10000111 &
#1360000
1!
0#
10
1/
11
12
0+
0,
0-
1.
b1000 %
b10001000 &
#1370000
0!
1"
00
1+
b1001 %
b10001001 &
#1380000
10
0/
0+
1,
b1010 %
b10001010 &
#1390000
00
1+
b1011 %
b10001011 &
#1400000
10
1/
01
0+
0,
1-
b1100 %
b10001100 &
#1410000
00
1+
b1101 %
b10001101 &
#1420000
10
0/
0+
1,
b1110 %
b10001110 &
#1430000
00
1+
b1111 %
b10001111 &
#1440000
0"
1#
1/
11
02
0+
0,
0-
0.
1'
b0 %
b1001 $
b10010000 &
#1450000
10
1+
b1 %
b10010001 &
#1460000
00
0/
0+
1,
b10 %
b10010010 &
#1470000
10
1+
b11 %
b10010011 &
#1480000
00
1/
01
0+
0,
1-
b100 %
b10010100 &
#1490000
10
1+
b101 %
b10010101 &
#1500000
00
0/
0+
1,
b110 %
b10010110 &
#1510000
10
1+
b111 %
b10010111 &
#1520000
1#
00
1/
11
12
0+
0,
0-
1.
b1000 %
b10011000 &
#1530000
0#
1!
10
1+
b1001 %
b10011001 &
#1540000
0#
0!
1"
00
0/
0+
1,
b1010 %
b10011010 &
#1550000
10
1+
b1011 %
b10011011 &
#1560000
00
1/
01
0+
0,
1-
b1100 %
b10011100 &
#1570000
10
1+
b1101 %
b10011101 &
#1580000
00
0/
0+
1,
b1110 %
b10011110 &
#1590000
10
1+
b1111 %
b10011111 &
#1600000
0"
1#
11
02
0+
0,
0-
0.
0'
1(
b0 %
b1010 $
b10100000 &
#1610000
00
1+
b1 %
b10100001 &
#1620000
10
1/
0+
1,
b10 %
b10100010 &
#1630000
00
1+
b11 %
b10100011 &
#1640000
10
0/
01
0+
0,
1-
b100 %
b10100100 &
#1650000
00
1+
b101 %
b10100101 &
#1660000
10
1/
0+
1,
b110 %
b10100110 &
#1670000
00
1+
b111 %
b10100111 &
#1680000
1#
10
0/
11
12
0+
0,
0-
1.
b1000 %
b10101000 &
#1690000
00
1+
b1001 %
b10101001 &
#1700000
0#
1!
0"
10
1/
0+
1,
b1010 %
b10101010 &
#1710000
0!
1"
00
1+
b1011 %
b10101011 &
#1720000
0#
10
0/
01
0+
0,
1-
b1100 %
b10101100 &
#1730000
00
1+
b1101 %
b10101101 &
#1740000
10
1/
0+
1,
b1110 %
b10101110 &
#1750000
00
1+
b1111 %
b10101111 &
#1760000
0"
1#
0/
11
02
0+
0,
0-
0.
1'
b0 %
b1011 $
b10110000 &
#1770000
10
1+
b1 %
b10110001 &
#1780000
00
1/
0+
1,
b10 %
b10110010 &
#1790000
10
1+
b11 %
b10110011 &
#1800000
00
0/
01
0+
0,
1-
b100 %
b10110100 &
#1810000
10
1+
b101 %
b10110101 &
#1820000
00
1/
0+
1,
b110 %
b10110110 &
#1830000
10
1+
b111 %
b10110111 &
#1840000
0!
1#
00
0/
11
12
0+
0,
0-
1.
b1000 %
b10111000 &
#1850000
10
1+
b1001 %
b10111001 &
#1860000
1#
00
1/
0+
1,
b1010 %
b10111010 &
#1870000
0#
1!
10
1+
b1011 %
b10111011 &
#1880000
0#
1"
0!
00
0/
01
0+
0,
1-
b1100 %
b10111100 &
#1890000
10
1+
b1101 %
b10111101 &
#1900000
00
1/
0+
1,
b1110 %
b10111110 &
#1910000
10
1+
b1111 %
b10111111 &
#1920000
0"
1#
02
0+
0,
0-
0.
0'
0(
1)
b0 %
b1100 $
b11000000 &
#1930000
00
1+
b1 %
b11000001 &
#1940000
10
0/
0+
1,
b10 %
b11000010 &
#1950000
00
1+
b11 %
b11000011 &
#1960000
10
1/
11
0+
0,
1-
b100 %
b11000100 &
#1970000
00
1+
b101 %
b11000101 &
#1980000
10
0/
0+
1,
b110 %
b11000110 &
#1990000
00
1+
b111 %
b11000111 &
#2000000
1#
10
1/
01
12
0+
0,
0-
1.
b1000 %
b11001000 &
#2010000
00
1+
b1001 %
b11001001 &
#2020000
10
0/
0+
1,
b1010 %
b11001010 &
#2030000
00
1+
b1011 %
b11001011 &
#2040000
1!
0#
10
1/
11
0+
0,
1-
b1100 %
b11001100 &
#2050000
0!
1"
00
1+
b1101 %
b11001101 &
#2060000
10
0/
0+
1,
b1110 %
b11001110 &
#2070000
00
1+
b1111 %
b11001111 &
#2080000
0"
1#
1/
01
02
0+
0,
0-
0.
1'
b0 %
b1101 $
b11010000 &
#2090000
10
1+
b1 %
b11010001 &
#2100000
00
0/
0+
1,
b10 %
b11010010 &
#2110000
10
1+
b11 %
b11010011 &
#2120000
00
1/
11
0+
0,
1-
b100 %
b11010100 &
#2130000
10
1+
b101 %
b11010101 &
#2140000
00
0/
0+
1,
b110 %
b11010110 &
#2150000
10
1+
b111 %
b11010111 &
#2160000
1#
00
1/
01
12
0+
0,
0-
1.
b1000 %
b11011000 &
#2170000
10
1+
b1001 %
b11011001 &
#2180000
00
0/
0+
1,
b1010 %
b11011010 &
#2190000
10
1+
b1011 %
b11011011 &
#2200000
1#
00
1/
11
0+
0,
1-
b1100 %
b11011100 &
#2210000
0#
1!
10
1+
b1101 %
b11011101 &
#2220000
0#
0!
1"
00
0/
0+
1,
b1110 %
b11011110 &
#2230000
10
1+
b1111 %
b11011111 &
#2240000
0"
1#
01
02
0+
0,
0-
0.
0'
1(
b0 %
b1110 $
b11100000 &
#2250000
00
1+
b1 %
b11100001 &
#2260000
10
1/
0+
1,
b10 %
b11100010 &
#2270000
00
1+
b11 %
b11100011 &
#2280000
10
0/
11
0+
0,
1-
b100 %
b11100100 &
#2290000
00
1+
b101 %
b11100101 &
#2300000
10
1/
0+
1,
b110 %
b11100110 &
#2310000
00
1+
b111 %
b11100111 &
#2320000
1#
10
0/
01
12
0+
0,
0-
1.
b1000 %
b11101000 &
#2330000
00
1+
b1001 %
b11101001 &
#2340000
10
1/
0+
1,
b1010 %
b11101010 &
#2350000
00
1+
b1011 %
b11101011 &
#2360000
1#
10
0/
11
0+
0,
1-
b1100 %
b11101100 &
#2370000
00
1+
b1101 %
b11101101 &
#2380000
0#
1!
0"
10
1/
0+
1,
b1110 %
b11101110 &
#2390000
0!
1"
00
1+
b1111 %
b11101111 &
#2400000
0"
1#
0/
01
02
0+
0,
0-
0.
1'
b0 %
b1111 $
b11110000 &
#2410000
10
1+
b1 %
b11110001 &
#2420000
00
1/
0+
1,
b10 %
b11110010 &
#2430000
10
1+
b11 %
b11110011 &
#2440000
00
0/
11
0+
0,
1-
b100 %
b11110100 &
#2450000
10
1+
b101 %
b11110101 &
#2460000
00
1/
0+
1,
b110 %
b11110110 &
#2470000
10
1+
b111 %
b11110111 &
#2480000
0!
1#
00
0/
01
12
0+
0,
0-
1.
b1000 %
b11111000 &
#2490000
10
1+
b1001 %
b11111001 &
#2500000
00
1/
0+
1,
b1010 %
b11111010 &
#2510000
10
1+
b1011 %
b11111011 &
#2520000
1#
0!
00
0/
11
0+
0,
1-
b1100 %
b11111100 &
#2530000
10
1+
b1101 %
b11111101 &
#2540000
1#
00
1/
0+
1,
b1110 %
b11111110 &
#2550000
0#
1!
10
1+
b1111 %
b11111111 &
#2560000
b100000000 &
